tasepy/__init__.py
tasepy/main.py
tasepy/py.typed
tasepy/client/__init__.py
tasepy/client/base_client.py
tasepy/client/client.py
tasepy/client/funds.py
tasepy/client/indices_basic.py
tasepy/client/indices_online.py
tasepy/client/request_callable.py
tasepy/client/securities_basic.py
tasepy/endpoints/__init__.py
tasepy/endpoints/endpoints.yaml
tasepy/endpoints/factories/__init__.py
tasepy/endpoints/factories/interfaces.py
tasepy/endpoints/factories/yaml_factory.py
tasepy/requests_/__init__.py
tasepy/requests_/enums.py
tasepy/requests_/headers.py
tasepy/requests_/parameters.py
tasepy/requests_/resources.py
tasepy/requests_/urls.py
tasepy/responses/__init__.py
tasepy/responses/responses.py
tasepy/responses/funds/__init__.py
tasepy/responses/funds/currency_exposure.py
tasepy/responses/funds/distribution_commission.py
tasepy/responses/funds/fund_list.py
tasepy/responses/funds/fund_type.py
tasepy/responses/funds/listing_status.py
tasepy/responses/funds/mutual_fund_classification.py
tasepy/responses/funds/payment_policy.py
tasepy/responses/funds/share_exposure.py
tasepy/responses/funds/stock_exchange.py
tasepy/responses/funds/tax_status.py
tasepy/responses/funds/tracking_fund_classification.py
tasepy/responses/funds/underlyting_asset.py
tasepy/responses/indices_basic/__init__.py
tasepy/responses/indices_basic/index_components.py
tasepy/responses/indices_basic/indices_list.py
tasepy/responses/indices_online/__init__.py
tasepy/responses/indices_online/intraday.py
tasepy/responses/indices_online/last_rate.py
tasepy/responses/indices_online/trading_rate_types.py
tasepy/responses/securities_basic/__init__.py
tasepy/responses/securities_basic/companies_list.py
tasepy/responses/securities_basic/delisted_securities_list.py
tasepy/responses/securities_basic/illiquid_maintenance_suspension_list.py
tasepy/responses/securities_basic/securities_types.py
tasepy/responses/securities_basic/trade_securities_list.py
tasepy/responses/securities_basic/trading_code_list.py
tasepy-0.2.0.dist-info/licenses/LICENSE
tasepy-0.2.0.dist-info/METADATA
tasepy-0.2.0.dist-info/WHEEL
tasepy-0.2.0.dist-info/top_level.txt
tasepy-0.2.0.dist-info/RECORD
