Metadata-Version: 2.4
Name: tasepy
Version: 0.2.0
Summary: A comprehensive Python SDK for accessing the Tel Aviv Stock Exchange (TASE) DataWise API
Author-email: Eliyahu Arlev <eliyahu.arlev@gmail.com>
License: MIT
Project-URL: Homepage, https://github.com/eliyahuA/tasepy
Project-URL: Repository, https://github.com/eliyahuA/tasepy.git
Project-URL: Bug Tracker, https://github.com/eliyahuA/tasepy/issues
Keywords: tase,stock-exchange,finance,api,sdk,tel-aviv
Classifier: Development Status :: 4 - Beta
Classifier: Intended Audience :: Developers
Classifier: Intended Audience :: Financial and Insurance Industry
Classifier: License :: OSI Approved :: MIT License
Classifier: Operating System :: OS Independent
Classifier: Programming Language :: Python :: 3
Classifier: Programming Language :: Python :: 3.10
Classifier: Programming Language :: Python :: 3.11
Classifier: Programming Language :: Python :: 3.12
Classifier: Programming Language :: Python :: 3.13
Classifier: Topic :: Office/Business :: Financial
Classifier: Topic :: Software Development :: Libraries :: Python Modules
Classifier: Typing :: Typed
Requires-Python: >=3.10
License-File: LICENSE
Requires-Dist: requests~=2.32.3
Requires-Dist: pydantic~=2.11.4
Requires-Dist: PyYAML~=6.0.2
Requires-Dist: typeguard~=4.4.2
Requires-Dist: beautifulsoup4~=4.13.4
Dynamic: license-file
